<?xml version="1.0" encoding="UTF-8"?>
<services xmlns="http://schemas.haulmont.com/cuba/rest-services-v2.xsd">
    <service name="placeur_RatingService">
        <method name="makeRecommendation">
            <param name="id"/>
        </method>
        <method name="getTopPlaces"/>
    </service>
    <service name="placeur_AuthorizationService">
        <method name="signin">
            <param name="nickname"/>
            <param name="password"/>
        </method>
        <method name="signup">
            <param name="nickname"/>
            <param name="password"/>
            <param name="cityId"/>
        </method>
    </service>
</services>